digly/__init__.py
digly/browser.py
digly/clarifai_util.py
digly/comment_util.py
digly/commenters_util.py
digly/constants.py
digly/database_engine.py
digly/digly.py
digly/event.py
digly/exceptions.py
digly/feed_util.py
digly/file_manager.py
digly/like_util.py
digly/login_util.py
digly/monkey_patcher.py
digly/pods_util.py
digly/print_log_writer.py
digly/quota_supervisor.py
digly/relationship_tools.py
digly/settings.py
digly/story_util.py
digly/text_analytics.py
digly/time_util.py
digly/unfollow_util.py
digly/util.py
digly/xpath.py
digly/xpath_compile.py
digly/firefox_extension/arrive.js
digly/firefox_extension/content.js
digly/firefox_extension/manifest.json
digly/plugins/__init__.py
digly/plugins/telegram_util.py
digly-0.1.0.dist-info/LICENSE
digly-0.1.0.dist-info/METADATA
digly-0.1.0.dist-info/WHEEL
digly-0.1.0.dist-info/entry_points.txt
digly-0.1.0.dist-info/top_level.txt
digly-0.1.0.dist-info/RECORD
