Metadata-Version: 2.1
Name: digly
Version: 0.1.0
Summary: Tool for automated Instagram interactions
Home-page: https://github.com/CMSHostingLLC/digly
Author: Digly
Maintainer: Digly
License: GPLv3
Download-URL: https://github.com/CMSHostingLLC/digly/archive/master.zip
Project-URL: Source, https://github.com/CMSHostingLLC/digly/tree/master/digly
Keywords: digly instagram automation          marketing promotion bot selenium
Platform: linux
Platform: linux2
Platform: darwin
Classifier: Environment :: Console
Classifier: Environment :: MacOS X
Classifier: Environment :: Web Environment
Classifier: Operating System :: POSIX :: Linux
Classifier: Operating System :: MacOS :: MacOS X
Classifier: Operating System :: Unix
Classifier: Programming Language :: Python
Classifier: Programming Language :: JavaScript
Classifier: Programming Language :: SQL
Classifier: Programming Language :: Python :: 3
Classifier: Programming Language :: Python :: 3.4
Classifier: Programming Language :: Python :: 3.5
Classifier: Programming Language :: Python :: 3.6
Classifier: Programming Language :: Python :: 3.7
Requires-Python: >=3, !=3.0.*, !=3.1.*, !=3.2.*, !=3.3.*
Requires-Dist: certifi (>=2018.10.15)
Requires-Dist: chardet (>=3.0.4)
Requires-Dist: clarifai (>=2.4.1)
Requires-Dist: configparser (>=3.5.0)
Requires-Dist: EasyProcess (>=0.2.3)
Requires-Dist: emoji (>=0.5.1)
Requires-Dist: future (>=0.17.1)
Requires-Dist: grpcio (>=1.16.1)
Requires-Dist: idna (>=2.7)
Requires-Dist: jsonschema (<3,>=2.6.0)
Requires-Dist: plyer (>=1.3.1)
Requires-Dist: protobuf (>=3.6.1)
Requires-Dist: requests (>=2.20.1)
Requires-Dist: selenium (>=3.141.0)
Requires-Dist: six (>=1.11.0)
Requires-Dist: urllib3 (>=1.24.1)
Requires-Dist: regex (>=2018.11.22)
Requires-Dist: MeaningCloud-python (>=1.1.1)
Requires-Dist: PyYAML (>=3.13)
Requires-Dist: webdriverdownloader
Requires-Dist: python-telegram-bot (>=12.0.0)
Requires-Dist: PyVirtualDisplay (>=0.2.1) ; sys_platform != "win32"
Provides-Extra: test
Requires-Dist: tox ; extra == 'test'
Requires-Dist: virtualenv ; extra == 'test'
Requires-Dist: tox-venv ; extra == 'test'
